marimo_utils/__init__.py
marimo_utils/display.py
marimo_utils/py.typed
marimo_utils-0.1.0.dist-info/METADATA
marimo_utils-0.1.0.dist-info/WHEEL
marimo_utils-0.1.0.dist-info/licenses/LICENSE
marimo_utils-0.1.0.dist-info/RECORD
