Metadata-Version: 2.4
Name: marimo-utils
Version: 0.1.0
Summary: Utilities for working with marimo notebooks, including Pydantic model display
Project-URL: Homepage, https://github.com/drothermel/marimo_utils
Project-URL: Repository, https://github.com/drothermel/marimo_utils
Author-email: Danielle Rothermel <danielle.rothermel@gmail.com>
License-Expression: MIT
License-File: LICENSE
Keywords: display,marimo,notebooks,pydantic
Classifier: Development Status :: 3 - Alpha
Classifier: Intended Audience :: Developers
Classifier: License :: OSI Approved :: MIT License
Classifier: Programming Language :: Python :: 3
Classifier: Programming Language :: Python :: 3.12
Classifier: Topic :: Software Development :: Libraries :: Python Modules
Requires-Python: >=3.12
Requires-Dist: marimo>=0.19.4
Requires-Dist: pydantic>=2.12.5
